odoo/addons/sale_stock_available_to_promise_release/README.rst
odoo/addons/sale_stock_available_to_promise_release/__init__.py
odoo/addons/sale_stock_available_to_promise_release/__manifest__.py
odoo/addons/sale_stock_available_to_promise_release/i18n/de.po
odoo/addons/sale_stock_available_to_promise_release/i18n/es_AR.po
odoo/addons/sale_stock_available_to_promise_release/i18n/fr.po
odoo/addons/sale_stock_available_to_promise_release/i18n/fr_CH.po
odoo/addons/sale_stock_available_to_promise_release/i18n/it.po
odoo/addons/sale_stock_available_to_promise_release/i18n/sale_stock_available_to_promise_release.pot
odoo/addons/sale_stock_available_to_promise_release/models/__init__.py
odoo/addons/sale_stock_available_to_promise_release/models/product_product.py
odoo/addons/sale_stock_available_to_promise_release/models/res_company.py
odoo/addons/sale_stock_available_to_promise_release/models/res_config_settings.py
odoo/addons/sale_stock_available_to_promise_release/models/sale_order.py
odoo/addons/sale_stock_available_to_promise_release/models/sale_order_line.py
odoo/addons/sale_stock_available_to_promise_release/models/stock_move.py
odoo/addons/sale_stock_available_to_promise_release/readme/CONTRIBUTORS.md
odoo/addons/sale_stock_available_to_promise_release/readme/CREDITS.md
odoo/addons/sale_stock_available_to_promise_release/readme/DESCRIPTION.md
odoo/addons/sale_stock_available_to_promise_release/reports/sale_order.xml
odoo/addons/sale_stock_available_to_promise_release/static/description/icon.png
odoo/addons/sale_stock_available_to_promise_release/static/description/index.html
odoo/addons/sale_stock_available_to_promise_release/tests/__init__.py
odoo/addons/sale_stock_available_to_promise_release/tests/common.py
odoo/addons/sale_stock_available_to_promise_release/tests/test_sale_line_availability_status.py
odoo/addons/sale_stock_available_to_promise_release/tests/test_sale_ok_expected_date.py
odoo_addon_sale_stock_available_to_promise_release-18.0.2.0.0.1.dist-info/METADATA
odoo_addon_sale_stock_available_to_promise_release-18.0.2.0.0.1.dist-info/WHEEL
odoo_addon_sale_stock_available_to_promise_release-18.0.2.0.0.1.dist-info/top_level.txt
odoo_addon_sale_stock_available_to_promise_release-18.0.2.0.0.1.dist-info/RECORD
